pybtreeplus/__init__.py
pybtreeplus/bptree.py
pybtreeplus-0.0.3.dist-info/LICENSE.md
pybtreeplus-0.0.3.dist-info/METADATA
pybtreeplus-0.0.3.dist-info/WHEEL
pybtreeplus-0.0.3.dist-info/top_level.txt
pybtreeplus-0.0.3.dist-info/RECORD
