Metadata-Version: 2.1
Name: pybtreeplus
Version: 0.0.3
Summary: pybtreeplus - python implementation of a B+-Tree in a heap file
Home-page: https://github.com/kr-g/pybtreeplus
Author: k.r. goger
Author-email: k.r.goger+pybtreeplus@gmail.com
License: UNKNOWN
Keywords: implementation of a B+-Tree storage memory management pyheapfile
Platform: UNKNOWN
Classifier: Development Status :: 3 - Alpha
Classifier: Operating System :: POSIX :: Linux
Classifier: Intended Audience :: Developers
Classifier: Programming Language :: Python :: 3
Classifier: License :: OSI Approved :: GNU Affero General Public License v3 or later (AGPLv3+)
Requires-Python: >=3.6
Requires-Dist: pybtreecore
